fibgrid/__init__.py
fibgrid/construction.py
fibgrid/realization.py
fibgrid/files/fibgrid_sphere_n1650000.nc
fibgrid/files/fibgrid_sphere_n430000.nc
fibgrid/files/fibgrid_sphere_n6600000.nc
fibgrid/files/fibgrid_wgs84_n1650000.nc
fibgrid/files/fibgrid_wgs84_n430000.nc
fibgrid/files/fibgrid_wgs84_n6600000.nc
fibgrid-0.0.7.dist-info/licenses/LICENSE.txt
fibgrid-0.0.7.dist-info/METADATA
fibgrid-0.0.7.dist-info/WHEEL
fibgrid-0.0.7.dist-info/top_level.txt
fibgrid-0.0.7.dist-info/RECORD
